{
  "m_GameObject": {
    "m_FileID": 0,
    "m_PathID": -183747650856433220
  },
  "m_Enabled": 1,
  "m_Script": {
    "m_FileID": 0,
    "m_PathID": 7361653699770502806
  },
  "m_Name": "",
  "_objectReferences": [
    {
      "m_FileID": 0,
      "m_PathID": -2948449217213202842
    },
    {
      "m_FileID": 0,
      "m_PathID": 5951931033150917537
    },
    {
      "m_FileID": 0,
      "m_PathID": 5951931033150917537
    },
    {
      "m_FileID": 0,
      "m_PathID": 5951931033150917537
    },
    {
      "m_FileID": 0,
      "m_PathID": 7308359977975310421
    },
    {
      "m_FileID": 0,
      "m_PathID": 5951931033150917537
    },
    {
      "m_FileID": 0,
      "m_PathID": 5951931033150917537
    },
    {
      "m_FileID": 0,
      "m_PathID": 5951931033150917537
    },
    {
      "m_FileID": 0,
      "m_PathID": 5951931033150917537
    },
    {
      "m_FileID": 0,
      "m_PathID": 5951931033150917537
    },
    {
      "m_FileID": 0,
      "m_PathID": 5951931033150917537
    },
    {
      "m_FileID": 0,
      "m_PathID": 5935056955829862004
    }
  ],
  "_serializedStateKeys": [
    "OverrideBehaviors",
    "TargetBehaviors",
    "MovementBehaviors",
    "AttackBehaviors",
    "OtherBehaviors"
  ],
  "_serializedStateValues": [
    "[]",
    "[{\"Radius\":35.0,\"LineOfSight\":true,\"ObjectPermanence\":true,\"SearchInterval\":0.25,\"PauseOnTargetSwitch\":false,\"PauseTime\":0.25,\"$type\":\"TargetPlayerBehavior\"}]",
    "[{\"StopWhenInRange\":true,\"CustomRange\":6.0,\"LineOfSight\":false,\"ReturnToSpawn\":true,\"SpawnTetherDistance\":0.0,\"PathInterval\":0.5,\"SpecifyRange\":false,\"MinActiveRange\":0.0,\"MaxActiveRange\":0.0,\"$type\":\"SeekTargetBehavior\"}]",
    "[{\"Time\":2.0,\"PlayDirectionalAnimation\":\"throne_awaken\",\"SetDefaultDirectionalAnimation\":\"throne_flying_idle\",\"EndOnDamage\":false,\"$type\":\"InitialAttackDelayBehavior\"},{\"ShareCooldowns\":false,\"AttackBehaviors\":[{\"NickName\":\"Spin Shoot\",\"Probability\":1.0,\"Behavior\":{\"ShootPoint\":0,\"BulletScript\":{\"scriptTypeName\":\"BulletKingCrazySpinHard1\"},\"PreventConcurrentAttacks\":false,\"spinBeginAnim\":\"spin_begin\",\"spinAnim\":\"spin\",\"spinEndAnim\":\"spin_end\",\"SpawnMuzzleVfx\":true,\"VfxMidDelay\":0.0199999995529652,\"spinVfx\":null,\"Cooldown\":10.0,\"CooldownVariance\":0.0,\"AttackCooldown\":0.5,\"GlobalCooldown\":0.0,\"InitialCooldown\":0.0,\"InitialCooldownVariance\":0.0,\"GroupName\":null,\"GroupCooldown\":0.0,\"MinRange\":0.0,\"Range\":0.0,\"MinWallDistance\":0.0,\"MaxEnemiesInRoom\":0.0,\"MinHealthThreshold\":0.0,\"MaxHealthThreshold\":1.0,\"HealthThresholds\":[],\"AccumulateHealthThresholds\":true,\"targetAreaStyle\":null,\"IsBlackPhantom\":false,\"resetCooldownOnDamage\":null,\"RequiresLineOfSight\":false,\"MaxUsages\":0,\"$type\":\"SpinAttackBehavior\"}},{\"NickName\":\"Homing Burst\",\"Probability\":1.0,\"Behavior\":{\"ShootPoint\":1,\"BulletScript\":{\"scriptTypeName\":\"BulletKingHomingBurst1\"},\"BulletName\":null,\"LeadAmount\":0.0,\"StopDuring\":\"None\",\"ImmobileDuringStop\":false,\"MoveSpeedModifier\":1.0,\"LockFacingDirection\":false,\"ContinueAimingDuringTell\":false,\"ReaimOnFire\":false,\"MultipleFireEvents\":false,\"RequiresTarget\":true,\"PreventTargetSwitching\":false,\"Uninterruptible\":false,\"ClearGoop\":false,\"ClearGoopRadius\":2.0,\"ShouldOverrideFireDirection\":false,\"OverrideFireDirection\":-1.0,\"SpecifyAiAnimator\":null,\"ChargeAnimation\":null,\"ChargeTime\":0.0,\"TellAnimation\":\"quick_tell\",\"FireAnimation\":\"quick\",\"PostFireAnimation\":null,\"HideGun\":true,\"OverrideBaseAnims\":false,\"OverrideIdleAnim\":null,\"OverrideMoveAnim\":null,\"UseVfx\":false,\"ChargeVfx\":null,\"TellVfx\":null,\"FireVfx\":null,\"Vfx\":null,\"EnabledDuringAttack\":[],\"Cooldown\":1.5,\"CooldownVariance\":0.0,\"AttackCooldown\":1.0,\"GlobalCooldown\":0.0,\"InitialCooldown\":0.0,\"InitialCooldownVariance\":0.0,\"GroupName\":null,\"GroupCooldown\":0.0,\"MinRange\":0.0,\"Range\":0.0,\"MinWallDistance\":0.0,\"MaxEnemiesInRoom\":0.0,\"MinHealthThreshold\":0.0,\"MaxHealthThreshold\":1.0,\"HealthThresholds\":[],\"AccumulateHealthThresholds\":true,\"targetAreaStyle\":null,\"IsBlackPhantom\":false,\"resetCooldownOnDamage\":null,\"RequiresLineOfSight\":false,\"MaxUsages\":0,\"$type\":\"ShootBehavior\"}},{\"NickName\":\"Quad Shot\",\"Probability\":1.0,\"Behavior\":{\"ShootPoint\":2,\"BulletScript\":{\"scriptTypeName\":\"BulletKingQuadShotHard1\"},\"BulletName\":null,\"LeadAmount\":0.0,\"StopDuring\":\"None\",\"ImmobileDuringStop\":false,\"MoveSpeedModifier\":1.0,\"LockFacingDirection\":false,\"ContinueAimingDuringTell\":false,\"ReaimOnFire\":false,\"MultipleFireEvents\":false,\"RequiresTarget\":true,\"PreventTargetSwitching\":false,\"Uninterruptible\":false,\"ClearGoop\":false,\"ClearGoopRadius\":2.0,\"ShouldOverrideFireDirection\":false,\"OverrideFireDirection\":-1.0,\"SpecifyAiAnimator\":null,\"ChargeAnimation\":null,\"ChargeTime\":0.0,\"TellAnimation\":\"slow_tell\",\"FireAnimation\":\"slow\",\"PostFireAnimation\":null,\"HideGun\":true,\"OverrideBaseAnims\":false,\"OverrideIdleAnim\":null,\"OverrideMoveAnim\":null,\"UseVfx\":false,\"ChargeVfx\":null,\"TellVfx\":null,\"FireVfx\":null,\"Vfx\":null,\"EnabledDuringAttack\":null,\"Cooldown\":1.5,\"CooldownVariance\":0.0,\"AttackCooldown\":0.5,\"GlobalCooldown\":0.0,\"InitialCooldown\":0.0,\"InitialCooldownVariance\":0.0,\"GroupName\":null,\"GroupCooldown\":0.0,\"MinRange\":0.0,\"Range\":0.0,\"MinWallDistance\":0.0,\"MaxEnemiesInRoom\":0.0,\"MinHealthThreshold\":0.0,\"MaxHealthThreshold\":1.0,\"HealthThresholds\":[],\"AccumulateHealthThresholds\":true,\"targetAreaStyle\":null,\"IsBlackPhantom\":false,\"resetCooldownOnDamage\":null,\"RequiresLineOfSight\":false,\"MaxUsages\":0,\"$type\":\"ShootBehavior\"}},{\"NickName\":\"Slam Burst (Hard)\",\"Probability\":1.0,\"Behavior\":{\"ShootPoint\":3,\"BulletScript\":{\"scriptTypeName\":\"BulletKingSlamHard1\"},\"BulletName\":null,\"LeadAmount\":0.0,\"StopDuring\":\"Attack\",\"ImmobileDuringStop\":false,\"MoveSpeedModifier\":1.0,\"LockFacingDirection\":false,\"ContinueAimingDuringTell\":false,\"ReaimOnFire\":false,\"MultipleFireEvents\":false,\"RequiresTarget\":true,\"PreventTargetSwitching\":false,\"Uninterruptible\":false,\"ClearGoop\":false,\"ClearGoopRadius\":2.0,\"ShouldOverrideFireDirection\":false,\"OverrideFireDirection\":-1.0,\"SpecifyAiAnimator\":null,\"ChargeAnimation\":null,\"ChargeTime\":0.0,\"TellAnimation\":\"pound_tell\",\"FireAnimation\":\"pound\",\"PostFireAnimation\":null,\"HideGun\":true,\"OverrideBaseAnims\":false,\"OverrideIdleAnim\":null,\"OverrideMoveAnim\":null,\"UseVfx\":false,\"ChargeVfx\":null,\"TellVfx\":null,\"FireVfx\":null,\"Vfx\":null,\"EnabledDuringAttack\":[],\"Cooldown\":1.5,\"CooldownVariance\":0.0,\"AttackCooldown\":0.5,\"GlobalCooldown\":0.0,\"InitialCooldown\":0.0,\"InitialCooldownVariance\":0.0,\"GroupName\":null,\"GroupCooldown\":0.0,\"MinRange\":0.0,\"Range\":0.0,\"MinWallDistance\":0.0,\"MaxEnemiesInRoom\":0.0,\"MinHealthThreshold\":0.0,\"MaxHealthThreshold\":1.0,\"HealthThresholds\":[],\"AccumulateHealthThresholds\":true,\"targetAreaStyle\":null,\"IsBlackPhantom\":false,\"resetCooldownOnDamage\":null,\"RequiresLineOfSight\":false,\"MaxUsages\":0,\"$type\":\"ShootBehavior\"}},{\"NickName\":\"Throw Goblet\",\"Probability\":1.0,\"Behavior\":{\"ShootPoint\":4,\"BulletScript\":null,\"BulletName\":\"goblet\",\"LeadAmount\":1.0,\"StopDuring\":\"Tell\",\"ImmobileDuringStop\":false,\"MoveSpeedModifier\":1.0,\"LockFacingDirection\":false,\"ContinueAimingDuringTell\":false,\"ReaimOnFire\":false,\"MultipleFireEvents\":false,\"RequiresTarget\":true,\"PreventTargetSwitching\":false,\"Uninterruptible\":false,\"ClearGoop\":false,\"ClearGoopRadius\":2.0,\"ShouldOverrideFireDirection\":false,\"OverrideFireDirection\":-1.0,\"SpecifyAiAnimator\":null,\"ChargeAnimation\":null,\"ChargeTime\":0.0,\"TellAnimation\":\"goblet_throw\",\"FireAnimation\":null,\"PostFireAnimation\":null,\"HideGun\":true,\"OverrideBaseAnims\":false,\"OverrideIdleAnim\":null,\"OverrideMoveAnim\":null,\"UseVfx\":false,\"ChargeVfx\":null,\"TellVfx\":null,\"FireVfx\":null,\"Vfx\":null,\"EnabledDuringAttack\":[],\"Cooldown\":8.0,\"CooldownVariance\":0.0,\"AttackCooldown\":0.800000011920929,\"GlobalCooldown\":0.0,\"InitialCooldown\":0.0,\"InitialCooldownVariance\":0.0,\"GroupName\":null,\"GroupCooldown\":0.0,\"MinRange\":0.0,\"Range\":0.0,\"MinWallDistance\":0.0,\"MaxEnemiesInRoom\":0.0,\"MinHealthThreshold\":0.0,\"MaxHealthThreshold\":1.0,\"HealthThresholds\":[],\"AccumulateHealthThresholds\":true,\"targetAreaStyle\":null,\"IsBlackPhantom\":false,\"resetCooldownOnDamage\":null,\"RequiresLineOfSight\":false,\"MaxUsages\":0,\"$type\":\"ShootBehavior\"}},{\"NickName\":\"Quickshot (Right)\",\"Probability\":4.0,\"Behavior\":{\"ShootPoint\":5,\"BulletScript\":{\"scriptTypeName\":\"BulletKingDirectedFireRightHard\"},\"BulletName\":null,\"LeadAmount\":0.0,\"StopDuring\":\"None\",\"ImmobileDuringStop\":false,\"MoveSpeedModifier\":1.0,\"LockFacingDirection\":false,\"ContinueAimingDuringTell\":false,\"ReaimOnFire\":false,\"MultipleFireEvents\":false,\"RequiresTarget\":true,\"PreventTargetSwitching\":false,\"Uninterruptible\":false,\"ClearGoop\":false,\"ClearGoopRadius\":2.0,\"ShouldOverrideFireDirection\":false,\"OverrideFireDirection\":-1.0,\"SpecifyAiAnimator\":null,\"ChargeAnimation\":null,\"ChargeTime\":0.0,\"TellAnimation\":\"slow_tell\",\"FireAnimation\":\"slow\",\"PostFireAnimation\":null,\"HideGun\":true,\"OverrideBaseAnims\":false,\"OverrideIdleAnim\":null,\"OverrideMoveAnim\":null,\"UseVfx\":false,\"ChargeVfx\":null,\"TellVfx\":null,\"FireVfx\":null,\"Vfx\":null,\"EnabledDuringAttack\":null,\"Cooldown\":0.0,\"CooldownVariance\":0.0,\"AttackCooldown\":0.0,\"GlobalCooldown\":0.0,\"InitialCooldown\":0.0,\"InitialCooldownVariance\":0.0,\"GroupName\":\"quickshot\",\"GroupCooldown\":0.649999976158142,\"MinRange\":0.0,\"Range\":0.0,\"MinWallDistance\":0.0,\"MaxEnemiesInRoom\":0.0,\"MinHealthThreshold\":0.0,\"MaxHealthThreshold\":1.0,\"HealthThresholds\":[],\"AccumulateHealthThresholds\":true,\"targetAreaStyle\":{\"AreaOriginOffset\":{\"x\":0.0,\"y\":-2.5},\"AreaDimensions\":{\"x\":20.0,\"y\":5.0},\"targetAreaOrigin\":\"ShootPoint\",\"$type\":\"ShootBehavior+RectFiringArea\"},\"IsBlackPhantom\":false,\"resetCooldownOnDamage\":null,\"RequiresLineOfSight\":false,\"MaxUsages\":0,\"$type\":\"ShootBehavior\"}},{\"NickName\":\"Quickshot (Left)\",\"Probability\":4.0,\"Behavior\":{\"ShootPoint\":6,\"BulletScript\":{\"scriptTypeName\":\"BulletKingDirectedFireLeftHard\"},\"BulletName\":null,\"LeadAmount\":0.0,\"StopDuring\":\"None\",\"ImmobileDuringStop\":false,\"MoveSpeedModifier\":1.0,\"LockFacingDirection\":false,\"ContinueAimingDuringTell\":false,\"ReaimOnFire\":false,\"MultipleFireEvents\":false,\"RequiresTarget\":true,\"PreventTargetSwitching\":false,\"Uninterruptible\":false,\"ClearGoop\":false,\"ClearGoopRadius\":2.0,\"ShouldOverrideFireDirection\":false,\"OverrideFireDirection\":-1.0,\"SpecifyAiAnimator\":null,\"ChargeAnimation\":null,\"ChargeTime\":0.0,\"TellAnimation\":\"slow_tell\",\"FireAnimation\":\"slow\",\"PostFireAnimation\":null,\"HideGun\":true,\"OverrideBaseAnims\":false,\"OverrideIdleAnim\":null,\"OverrideMoveAnim\":null,\"UseVfx\":false,\"ChargeVfx\":null,\"TellVfx\":null,\"FireVfx\":null,\"Vfx\":null,\"EnabledDuringAttack\":null,\"Cooldown\":0.0,\"CooldownVariance\":0.0,\"AttackCooldown\":0.0,\"GlobalCooldown\":0.0,\"InitialCooldown\":0.0,\"InitialCooldownVariance\":0.0,\"GroupName\":\"quickshot\",\"GroupCooldown\":0.649999976158142,\"MinRange\":0.0,\"Range\":0.0,\"MinWallDistance\":0.0,\"MaxEnemiesInRoom\":0.0,\"MinHealthThreshold\":0.0,\"MaxHealthThreshold\":1.0,\"HealthThresholds\":[],\"AccumulateHealthThresholds\":true,\"targetAreaStyle\":{\"AreaOriginOffset\":{\"x\":-20.0,\"y\":-2.5},\"AreaDimensions\":{\"x\":20.0,\"y\":5.0},\"targetAreaOrigin\":\"ShootPoint\",\"$type\":\"ShootBehavior+RectFiringArea\"},\"IsBlackPhantom\":false,\"resetCooldownOnDamage\":null,\"RequiresLineOfSight\":false,\"MaxUsages\":0,\"$type\":\"ShootBehavior\"}},{\"NickName\":\"Quickshot (Lower Left)\",\"Probability\":4.0,\"Behavior\":{\"ShootPoint\":7,\"BulletScript\":{\"scriptTypeName\":\"BulletKingDirectedFireDownLeftHard\"},\"BulletName\":null,\"LeadAmount\":0.0,\"StopDuring\":\"None\",\"ImmobileDuringStop\":false,\"MoveSpeedModifier\":1.0,\"LockFacingDirection\":false,\"ContinueAimingDuringTell\":false,\"ReaimOnFire\":false,\"MultipleFireEvents\":false,\"RequiresTarget\":true,\"PreventTargetSwitching\":false,\"Uninterruptible\":false,\"ClearGoop\":false,\"ClearGoopRadius\":2.0,\"ShouldOverrideFireDirection\":false,\"OverrideFireDirection\":-1.0,\"SpecifyAiAnimator\":null,\"ChargeAnimation\":null,\"ChargeTime\":0.0,\"TellAnimation\":\"slow_tell\",\"FireAnimation\":\"slow\",\"PostFireAnimation\":null,\"HideGun\":true,\"OverrideBaseAnims\":false,\"OverrideIdleAnim\":null,\"OverrideMoveAnim\":null,\"UseVfx\":false,\"ChargeVfx\":null,\"TellVfx\":null,\"FireVfx\":null,\"Vfx\":null,\"EnabledDuringAttack\":null,\"Cooldown\":0.0,\"CooldownVariance\":0.0,\"AttackCooldown\":0.0,\"GlobalCooldown\":0.0,\"InitialCooldown\":0.0,\"InitialCooldownVariance\":0.0,\"GroupName\":\"quickshot\",\"GroupCooldown\":0.649999976158142,\"MinRange\":0.0,\"Range\":0.0,\"MinWallDistance\":0.0,\"MaxEnemiesInRoom\":0.0,\"MinHealthThreshold\":0.0,\"MaxHealthThreshold\":1.0,\"HealthThresholds\":[],\"AccumulateHealthThresholds\":true,\"targetAreaStyle\":{\"StartAngle\":-120.0,\"SweepAngle\":-35.0,\"targetAreaOrigin\":\"ShootPoint\",\"$type\":\"ShootBehavior+ArcFiringArea\"},\"IsBlackPhantom\":false,\"resetCooldownOnDamage\":null,\"RequiresLineOfSight\":false,\"MaxUsages\":0,\"$type\":\"ShootBehavior\"}},{\"NickName\":\"Quickshot (Lower Right)\",\"Probability\":4.0,\"Behavior\":{\"ShootPoint\":8,\"BulletScript\":{\"scriptTypeName\":\"BulletKingDirectedFireDownRightHard\"},\"BulletName\":null,\"LeadAmount\":0.0,\"StopDuring\":\"None\",\"ImmobileDuringStop\":false,\"MoveSpeedModifier\":1.0,\"LockFacingDirection\":false,\"ContinueAimingDuringTell\":false,\"ReaimOnFire\":false,\"MultipleFireEvents\":false,\"RequiresTarget\":true,\"PreventTargetSwitching\":false,\"Uninterruptible\":false,\"ClearGoop\":false,\"ClearGoopRadius\":2.0,\"ShouldOverrideFireDirection\":false,\"OverrideFireDirection\":-1.0,\"SpecifyAiAnimator\":null,\"ChargeAnimation\":null,\"ChargeTime\":0.0,\"TellAnimation\":\"slow_tell\",\"FireAnimation\":\"slow\",\"PostFireAnimation\":null,\"HideGun\":true,\"OverrideBaseAnims\":false,\"OverrideIdleAnim\":null,\"OverrideMoveAnim\":null,\"UseVfx\":false,\"ChargeVfx\":null,\"TellVfx\":null,\"FireVfx\":null,\"Vfx\":null,\"EnabledDuringAttack\":null,\"Cooldown\":0.0,\"CooldownVariance\":0.0,\"AttackCooldown\":0.0,\"GlobalCooldown\":0.0,\"InitialCooldown\":0.0,\"InitialCooldownVariance\":0.0,\"GroupName\":\"quickshot\",\"GroupCooldown\":0.649999976158142,\"MinRange\":0.0,\"Range\":0.0,\"MinWallDistance\":0.0,\"MaxEnemiesInRoom\":0.0,\"MinHealthThreshold\":0.0,\"MaxHealthThreshold\":1.0,\"HealthThresholds\":[],\"AccumulateHealthThresholds\":true,\"targetAreaStyle\":{\"StartAngle\":-60.0,\"SweepAngle\":35.0,\"targetAreaOrigin\":\"ShootPoint\",\"$type\":\"ShootBehavior+ArcFiringArea\"},\"IsBlackPhantom\":false,\"resetCooldownOnDamage\":null,\"RequiresLineOfSight\":false,\"MaxUsages\":0,\"$type\":\"ShootBehavior\"}},{\"NickName\":\"Big Bullet North\",\"Probability\":1.0,\"Behavior\":{\"ShootPoint\":9,\"BulletScript\":{\"scriptTypeName\":\"BulletKingBigBulletUpHard1\"},\"BulletName\":null,\"LeadAmount\":0.0,\"StopDuring\":\"None\",\"ImmobileDuringStop\":false,\"MoveSpeedModifier\":1.0,\"LockFacingDirection\":false,\"ContinueAimingDuringTell\":false,\"ReaimOnFire\":false,\"MultipleFireEvents\":false,\"RequiresTarget\":true,\"PreventTargetSwitching\":false,\"Uninterruptible\":false,\"ClearGoop\":false,\"ClearGoopRadius\":2.0,\"ShouldOverrideFireDirection\":false,\"OverrideFireDirection\":-1.0,\"SpecifyAiAnimator\":null,\"ChargeAnimation\":null,\"ChargeTime\":0.0,\"TellAnimation\":\"mega_tell\",\"FireAnimation\":\"\",\"PostFireAnimation\":null,\"HideGun\":true,\"OverrideBaseAnims\":false,\"OverrideIdleAnim\":null,\"OverrideMoveAnim\":null,\"UseVfx\":false,\"ChargeVfx\":null,\"TellVfx\":null,\"FireVfx\":null,\"Vfx\":null,\"EnabledDuringAttack\":[],\"Cooldown\":1.0,\"CooldownVariance\":0.0,\"AttackCooldown\":0.5,\"GlobalCooldown\":0.0,\"InitialCooldown\":0.0,\"InitialCooldownVariance\":0.0,\"GroupName\":null,\"GroupCooldown\":0.0,\"MinRange\":0.0,\"Range\":0.0,\"MinWallDistance\":0.0,\"MaxEnemiesInRoom\":0.0,\"MinHealthThreshold\":0.0,\"MaxHealthThreshold\":1.0,\"HealthThresholds\":[],\"AccumulateHealthThresholds\":true,\"targetAreaStyle\":null,\"IsBlackPhantom\":false,\"resetCooldownOnDamage\":null,\"RequiresLineOfSight\":false,\"MaxUsages\":0,\"$type\":\"ShootBehavior\"}},{\"NickName\":\"Homing  Ring\",\"Probability\":2.0,\"Behavior\":{\"ShootPoint\":10,\"BulletScript\":{\"scriptTypeName\":\"BulletKingHomingRing1\"},\"BulletName\":null,\"LeadAmount\":0.0,\"StopDuring\":\"None\",\"ImmobileDuringStop\":false,\"MoveSpeedModifier\":1.0,\"LockFacingDirection\":false,\"ContinueAimingDuringTell\":false,\"ReaimOnFire\":false,\"MultipleFireEvents\":false,\"RequiresTarget\":true,\"PreventTargetSwitching\":false,\"Uninterruptible\":false,\"ClearGoop\":false,\"ClearGoopRadius\":2.0,\"ShouldOverrideFireDirection\":false,\"OverrideFireDirection\":-1.0,\"SpecifyAiAnimator\":null,\"ChargeAnimation\":null,\"ChargeTime\":0.0,\"TellAnimation\":\"mega_tell\",\"FireAnimation\":\"\",\"PostFireAnimation\":null,\"HideGun\":true,\"OverrideBaseAnims\":false,\"OverrideIdleAnim\":null,\"OverrideMoveAnim\":null,\"UseVfx\":false,\"ChargeVfx\":null,\"TellVfx\":null,\"FireVfx\":null,\"Vfx\":null,\"EnabledDuringAttack\":[],\"Cooldown\":8.0,\"CooldownVariance\":0.0,\"AttackCooldown\":0.0,\"GlobalCooldown\":0.0,\"InitialCooldown\":0.0,\"InitialCooldownVariance\":0.0,\"GroupName\":null,\"GroupCooldown\":0.0,\"MinRange\":0.0,\"Range\":0.0,\"MinWallDistance\":0.0,\"MaxEnemiesInRoom\":0.0,\"MinHealthThreshold\":0.0,\"MaxHealthThreshold\":1.0,\"HealthThresholds\":[],\"AccumulateHealthThresholds\":true,\"targetAreaStyle\":null,\"IsBlackPhantom\":false,\"resetCooldownOnDamage\":null,\"RequiresLineOfSight\":false,\"MaxUsages\":0,\"$type\":\"ShootBehavior\"}},{\"NickName\":\"Slam & Suck\",\"Probability\":4.0,\"Behavior\":{\"ShootPoint\":11,\"BulletScript\":{\"scriptTypeName\":\"BulletKingSuck1\"},\"BulletName\":null,\"LeadAmount\":0.0,\"StopDuring\":\"Attack\",\"ImmobileDuringStop\":false,\"MoveSpeedModifier\":1.0,\"LockFacingDirection\":false,\"ContinueAimingDuringTell\":false,\"ReaimOnFire\":false,\"MultipleFireEvents\":false,\"RequiresTarget\":true,\"PreventTargetSwitching\":false,\"Uninterruptible\":false,\"ClearGoop\":false,\"ClearGoopRadius\":2.0,\"ShouldOverrideFireDirection\":false,\"OverrideFireDirection\":0.0,\"SpecifyAiAnimator\":null,\"ChargeAnimation\":null,\"ChargeTime\":0.0,\"TellAnimation\":\"suck\",\"FireAnimation\":\"\",\"PostFireAnimation\":null,\"HideGun\":true,\"OverrideBaseAnims\":false,\"OverrideIdleAnim\":null,\"OverrideMoveAnim\":null,\"UseVfx\":false,\"ChargeVfx\":null,\"TellVfx\":null,\"FireVfx\":null,\"Vfx\":null,\"EnabledDuringAttack\":[],\"Cooldown\":15.0,\"CooldownVariance\":0.0,\"AttackCooldown\":0.5,\"GlobalCooldown\":0.0,\"InitialCooldown\":8.0,\"InitialCooldownVariance\":0.0,\"GroupName\":null,\"GroupCooldown\":0.0,\"MinRange\":0.0,\"Range\":0.0,\"MinWallDistance\":0.0,\"MaxEnemiesInRoom\":0.0,\"MinHealthThreshold\":0.0,\"MaxHealthThreshold\":1.0,\"HealthThresholds\":[],\"AccumulateHealthThresholds\":true,\"targetAreaStyle\":null,\"IsBlackPhantom\":false,\"resetCooldownOnDamage\":null,\"RequiresLineOfSight\":false,\"MaxUsages\":0,\"$type\":\"ShootBehavior\"}}],\"$type\":\"AttackBehaviorGroup\"}]",
    "[]"
  ],
  "InstantFirstTick": 0,
  "TickInterval": 0.1,
  "PostAwakenDelay": 0.0,
  "RemoveDelayOnReinforce": 0,
  "OverrideStartingFacingDirection": 0,
  "StartingFacingDirection": -90.0,
  "SkipTimingDifferentiator": 0
}