{
  "m_GameObject": {
    "m_FileID": 0,
    "m_PathID": -3563506391211167914
  },
  "m_Enabled": 1,
  "m_Script": {
    "m_FileID": 0,
    "m_PathID": -6032341579217542678
  },
  "m_Name": "",
  "ProxyEncounterGuid": "",
  "m_encounterGuid": "8c2d23e3ed404a75b2bbd1e599aa2d0b",
  "m_doNotificationOnEncounter": 1,
  "SuppressInInventory": 0,
  "m_journalData": {
    "SuppressInAmmonomicon": 0,
    "SuppressKnownState": 0,
    "DisplayOnLoadingScreen": 0,
    "RequiresLightBackgroundInLoadingScreen": 0,
    "PrimaryDisplayName": "#SHOTGUNCOFFEE_ENCNAME",
    "NotificationPanelDescription": "#SHOTGUNCOFFEE_SHORTDESC",
    "AmmonomiconFullEntry": "#SHOTGUNCOFFEE_LONGDESC",
    "AmmonomiconSprite": "shotgun_coffee_001",
    "IsEnemy": 0,
    "enemyPortraitSprite": {
      "m_FileID": 0,
      "m_PathID": 0
    },
    "SpecialIdentifier": 0
  },
  "m_ignoreDifferentiator": 0,
  "m_prerequisites": [],
  "m_usesPurpleNotifications": 0
}