{
  "m_GameObject": {
    "m_FileID": 0,
    "m_PathID": -1059381391104100410
  },
  "m_Enabled": 1,
  "m_Script": {
    "m_FileID": 0,
    "m_PathID": 479711498624462457
  },
  "m_Name": "",
  "AscentTime": 0.75,
  "AscentCurve": {
    "m_Curve": [
      {
        "time": 0.0,
        "value": 0.0,
        "inSlope": 0.0,
        "outSlope": 0.0
      },
      {
        "time": 1.0,
        "value": 1.0,
        "inSlope": 2.0,
        "outSlope": 2.0
      }
    ],
    "m_PreInfinity": 2,
    "m_PostInfinity": 2,
    "m_RotationOrder": 0
  },
  "HangTime": 0.25,
  "DescentTime": 1.25,
  "DescentCurve": {
    "m_Curve": [
      {
        "time": 0.0,
        "value": 1.0062499,
        "inSlope": 0.0,
        "outSlope": 0.0
      },
      {
        "time": 0.9957806,
        "value": -0.00624990463,
        "inSlope": -2.4400506,
        "outSlope": -2.4400506
      }
    ],
    "m_PreInfinity": 2,
    "m_PostInfinity": 2,
    "m_RotationOrder": 0
  },
  "MaxHeight": 30.0,
  "DownSprite": "rocket_white_red_down_001",
  "Variance": 1.0,
  "LeadPercentage": 0.33,
  "LandingTargetSprite": {
    "m_FileID": 2,
    "m_PathID": -4879166205475291646
  },
  "DoExplosion": 1,
  "ExplosionData": {
    "useDefaultExplosion": 0,
    "doDamage": 1,
    "forceUseThisRadius": 0,
    "damageRadius": 3.0,
    "damageToPlayer": 0.5,
    "damage": 30.0,
    "breakSecretWalls": 0,
    "secretWallsRadius": 4.5,
    "forcePreventSecretWallDamage": 0,
    "doDestroyProjectiles": 1,
    "doForce": 1,
    "pushRadius": 6.0,
    "force": 10.0,
    "debrisForce": 50.0,
    "preventPlayerForce": 0,
    "explosionDelay": 0.1,
    "usesComprehensiveDelay": 0,
    "comprehensiveDelay": 0.0,
    "effect": {
      "m_FileID": 2,
      "m_PathID": 5305378572671065930
    },
    "doScreenShake": 1,
    "ss": {
      "magnitude": 0.5,
      "speed": 6.5,
      "time": 0.07,
      "falloff": 0.0,
      "direction": {
        "x": 0.0,
        "y": 0.0
      },
      "vibrationType": 10,
      "simpleVibrationTime": 20,
      "simpleVibrationStrength": 20
    },
    "doStickyFriction": 1,
    "doExplosionRing": 1,
    "isFreezeExplosion": 0,
    "freezeRadius": 5.0,
    "freezeEffect": {
      "AffectsPlayers": 1,
      "AffectsEnemies": 1,
      "effectIdentifier": "effect",
      "resistanceType": 0,
      "stackMode": 0,
      "duration": 10.0,
      "maxStackedDuration": -1.0,
      "AppliesTint": 0,
      "TintColor": {
        "r": 1.0,
        "g": 1.0,
        "b": 1.0,
        "a": 0.5
      },
      "AppliesDeathTint": 0,
      "DeathTintColor": {
        "r": 0.388,
        "g": 0.388,
        "b": 0.388,
        "a": 1.0
      },
      "AppliesOutlineTint": 0,
      "OutlineTintColor": {
        "r": 0.0,
        "g": 0.0,
        "b": 0.0,
        "a": 1.0
      },
      "OverheadVFX": {
        "m_FileID": 0,
        "m_PathID": 0
      },
      "PlaysVFXOnActor": 0,
      "FreezeAmount": 10.0,
      "UnfreezeDamagePercent": 0.333,
      "FreezeCrystals": [],
      "crystalRot": 8,
      "crystalVariation": {
        "x": 0.05,
        "y": 0.05
      },
      "debrisMinForce": 5,
      "debrisMaxForce": 5,
      "debrisAngleVariance": 15.0,
      "vfxExplosion": {
        "m_FileID": 0,
        "m_PathID": 0
      }
    },
    "playDefaultSFX": 1,
    "IsChandelierExplosion": 0,
    "rotateEffectToNormal": 0,
    "ignoreList": [],
    "overrideRangeIndicatorEffect": {
      "m_FileID": 0,
      "m_PathID": 0
    }
  },
  "IgnoreExplosionQueues": 0,
  "SpawnVfx": {
    "type": 0,
    "effects": []
  },
  "SpawnObject": {
    "m_FileID": 0,
    "m_PathID": 0
  }
}